pynumerical/__init__.py
pynumerical/pynumerical.py
pynumerical-0.0.1.dist-info/LICENSE
pynumerical-0.0.1.dist-info/METADATA
pynumerical-0.0.1.dist-info/WHEEL
pynumerical-0.0.1.dist-info/top_level.txt
pynumerical-0.0.1.dist-info/RECORD
