Metadata-Version: 2.1
Name: pynumerical
Version: 0.0.1
Summary: Numerical methods for differentiation and integration
Home-page: https://github.com/abdanar/pynumerical
Author: Anar Abdullayev
Author-email: abdullaanar172@gmail.com
License: MIT
Platform: UNKNOWN
Classifier: Programming Language :: Python :: 3
Classifier: License :: OSI Approved :: MIT License
Classifier: Operating System :: OS Independent
Classifier: Intended Audience :: Science/Research
Classifier: Topic :: Scientific/Engineering :: Mathematics
Requires-Python: >=3.10
License-File: LICENSE
Requires-Dist: numpy
